snapspam/__init__.py
snapspam/__main__.py
snapspam/cli.py
snapspam/lmk.py
snapspam/ngl.py
snapspam/sendit.py
snapspam-0.2.0.dist-info/LICENSE
snapspam-0.2.0.dist-info/METADATA
snapspam-0.2.0.dist-info/WHEEL
snapspam-0.2.0.dist-info/entry_points.txt
snapspam-0.2.0.dist-info/top_level.txt
snapspam-0.2.0.dist-info/RECORD
