Metadata-Version: 2.1
Name: snapspam
Version: 0.2.0
Summary: Spam sendit, LMK, or NGL messages.
Home-page: https://github.com/MysteryBlokHed/snapspam
Author: Adam Thompson-Sharpe
Author-email: adamthompsonsharpe@gmail.com
License: UNKNOWN
Platform: UNKNOWN
Classifier: Intended Audience :: End Users/Desktop
Classifier: License :: OSI Approved :: GNU General Public License v3 (GPLv3)
Classifier: Natural Language :: English
Classifier: Operating System :: OS Independent
Classifier: Programming Language :: Python
Classifier: Programming Language :: Python :: 3
Classifier: Programming Language :: Python :: 3.6
Classifier: Programming Language :: Python :: 3.7
Classifier: Programming Language :: Python :: 3.8
Classifier: Programming Language :: Python :: 3.9
Classifier: Programming Language :: Python :: 3.10
Requires-Python: ~=3.6
License-File: LICENSE
Requires-Dist: beautifulsoup4 (~=4.9)
Requires-Dist: pysocks (~=1.7)
Requires-Dist: requests (~=2.25)
Requires-Dist: requests[socks] (~=2.25)
